lab_day3_02_schoolrisc/support/step3/src/schoolriscv/sr_cpu.vh
/*
 * schoolRISCV - small RISC-V CPU 
 *
 * originally based on Sarah L. Harris MIPS CPU 
 *                   & schoolMIPS project
 * 
 * Copyright(c) 2017-2020 Stanislav Zhelnio 
 *                        Aleksandr Romanov 
 */ 

//ALU commands
`define ALU_ADD     3'b000
`define ALU_OR      3'b001
`define ALU_SRL     3'b010
`define ALU_SLTU    3'b011
`define ALU_SUB     3'b100
`define ALU_MUL     3'b101

// instruction opcode
`define RVOP_ADDI   7'b0010011
`define RVOP_BEQ    7'b1100011
`define RVOP_LUI    7'b0110111
`define RVOP_BNE    7'b1100011
`define RVOP_ADD    7'b0110011
`define RVOP_OR     7'b0110011
`define RVOP_SRL    7'b0110011
`define RVOP_SLTU   7'b0110011
`define RVOP_SUB    7'b0110011
`define RVOP_MUL    7'b0110011

// instruction funct3
`define RVF3_ADDI   3'b000
`define RVF3_BEQ    3'b000
`define RVF3_BNE    3'b001
`define RVF3_ADD    3'b000
`define RVF3_OR     3'b110
`define RVF3_SRL    3'b101
`define RVF3_SLTU   3'b011
`define RVF3_SUB    3'b000
`define RVF3_ANY    3'b???
`define RVF3_MUL    3'b000

// instruction funct7
`define RVF7_ADD    7'b0000000
`define RVF7_OR     7'b0000000
`define RVF7_SRL    7'b0000000
`define RVF7_SLTU   7'b0000000
`define RVF7_SUB    7'b0100000
`define RVF7_ANY    7'b???????
`define RVF7_MUL    7'b0000001

lab_day3_02_schoolrisc/support/step2/src/schoolriscv/sr_control.v
/*
 * schoolRISCV - small RISC-V CPU 
 *
 * originally based on Sarah L. Harris MIPS CPU 
 *                   & schoolMIPS project
 * 
 * Copyright(c) 2017-2020 Stanislav Zhelnio 
 *                        Aleksandr Romanov 
 */ 


module sr_control
(
    input     [ 6:0] cmdOp,
    input     [ 2:0] cmdF3,
    input     [ 6:0] cmdF7,
    input            aluZero,
    output           pcSrc, 
    output reg       regWrite, 
    output reg       aluSrc,
    output reg       wdSrc,
    output reg [2:0] aluControl
);
    reg          branch;
    reg          condZero;
    assign pcSrc = branch & (aluZero == condZero);

    always @ (*) begin
        branch      = 1'b0;
        condZero    = 1'b0;
        regWrite    = 1'b0;
        aluSrc      = 1'b0;
        wdSrc       = 1'b0;
        aluControl  = `ALU_ADD;

        casez( {cmdF7, cmdF3, cmdOp} )
            { `RVF7_ADD,  `RVF3_ADD,  `RVOP_ADD  } : begin regWrite = 1'b1; aluControl = `ALU_ADD;  end
            { `RVF7_OR,   `RVF3_OR,   `RVOP_OR   } : begin regWrite = 1'b1; aluControl = `ALU_OR;   end
            { `RVF7_SRL,  `RVF3_SRL,  `RVOP_SRL  } : begin regWrite = 1'b1; aluControl = `ALU_SRL;  end
            { `RVF7_SLTU, `RVF3_SLTU, `RVOP_SLTU } : begin regWrite = 1'b1; aluControl = `ALU_SLTU; end
            { `RVF7_SUB,  `RVF3_SUB,  `RVOP_SUB  } : begin regWrite = 1'b1; aluControl = `ALU_SUB;  end

            { `RVF7_ANY,  `RVF3_ADDI, `RVOP_ADDI } : begin regWrite = 1'b1; aluSrc = 1'b1; aluControl = `ALU_ADD; end
            { `RVF7_ANY,  `RVF3_ANY,  `RVOP_LUI  } : begin regWrite = 1'b1; wdSrc  = 1'b1; end

            { `RVF7_ANY,  `RVF3_BEQ,  `RVOP_BEQ  } : begin branch = 1'b1; condZero = 1'b1; aluControl = `ALU_SUB; end
            { `RVF7_ANY,  `RVF3_BNE,  `RVOP_BNE  } : begin branch = 1'b1; aluControl = `ALU_SUB; end
        endcase
    end
endmodule

lab_day3_02_schoolrisc/support/step2/src/school_risk/sr_alu.v
/*
 * schoolRISCV - small RISC-V CPU 
 *
 * originally based on Sarah L. Harris MIPS CPU 
 *                   & schoolMIPS project
 * 
 * Copyright(c) 2017-2020 Stanislav Zhelnio 
 *                        Aleksandr Romanov 
 */ 


`include "sr_cpu.vh"

module sr_alu
(
    input  [31:0] srcA,
    input  [31:0] srcB,
    input  [ 2:0] oper,
    output        zero,
    output reg [31:0] result
);
    always @ (*) begin
        case (oper)
            default   : result = srcA + srcB;
            `ALU_ADD  : result = srcA + srcB;
            `ALU_OR   : result = srcA | srcB;
            `ALU_SRL  : result = srcA >> srcB [4:0];
            `ALU_SLTU : result = (srcA < srcB) ? 1 : 0;
            `ALU_SUB : result = srcA - srcB;
        endcase
    end

    assign zero   = (result == 0);


endmodule

lab_day3_02_schoolrisc/support/step2/src/schoolriscv/sm_register_file_vc.v
/*
 * schoolRISCV - small RISC-V CPU 
 *
 * originally based on Sarah L. Harris MIPS CPU 
 *                   & schoolMIPS project
 * 
 * Copyright(c) 2017-2020 Stanislav Zhelnio 
 *                        Aleksandr Romanov 
 */ 

 module sm_register_file_vc
(
    input         clk,
    input  [ 4:0] a0,
    input  [ 4:0] a1,
    input  [ 4:0] a2,
    input  [ 4:0] a3,
    output [31:0] rd0,
    output [31:0] rd1,
    output [31:0] rd2,
    input  [31:0] wd3,
    input         we3,

    input   [31:0]  vcu_reg_rdata      

);
    reg [31:0] rf [31:0];

    assign rd0 = (a0 != 0) ? rf [a0] : 32'b0;
    assign rd1 = (a1 != 0) ? rf [a1] : 32'b0;
    assign rd2 = (a2 != 0) ? rf [a2] : 32'b0;

    always @ (posedge clk) begin
        if( a3!=5'b11110 )
            if(we3) rf [a3] <= wd3;

        rf[5'b11110] <= vcu_reg_rdata;
    end
endmodule

lab_day3_02_schoolrisc/support/step2/src/schoolriscv/sr_decode.v
/*
 * schoolRISCV - small RISC-V CPU 
 *
 * originally based on Sarah L. Harris MIPS CPU 
 *                   & schoolMIPS project
 * 
 * Copyright(c) 2017-2020 Stanislav Zhelnio 
 *                        Aleksandr Romanov 
 */ 


module sr_decode
(
    input      [31:0] instr,
    output     [ 6:0] cmdOp,
    output     [ 4:0] rd,
    output     [ 2:0] cmdF3,
    output     [ 4:0] rs1,
    output     [ 4:0] rs2,
    output     [ 6:0] cmdF7,
    output reg [31:0] immI,
    output reg [31:0] immB,
    output reg [31:0] immU 
);
    assign cmdOp = instr[ 6: 0];
    assign rd    = instr[11: 7];
    assign cmdF3 = instr[14:12];
    assign rs1   = instr[19:15];
    assign rs2   = instr[24:20];
    assign cmdF7 = instr[31:25];

    // I-immediate
    always @ (*) begin
        immI[10: 0] = instr[30:20];
        immI[31:11] = { 21 {instr[31]} };
    end

    // B-immediate
    always @ (*) begin
        immB[    0] = 1'b0;
        immB[ 4: 1] = instr[11:8];
        immB[10: 5] = instr[30:25];
        immB[   11] = instr[7];
        immB[31:12] = { 20 {instr[31]} };
    end

    // U-immediate
    always @ (*) begin
        immU[11: 0] = 12'b0;
        immU[31:12] = instr[31:12];
    end

endmodule

lab_day3_02_schoolrisc/openline/designs/schoolriscv/src/sm_register.v
/*
 * schoolRISCV - small RISC-V CPU 
 *
 * originally based on Sarah L. Harris MIPS CPU 
 *                   & schoolMIPS project
 * 
 * Copyright(c) 2017-2020 Stanislav Zhelnio 
 *                        Aleksandr Romanov 
 */ 

module sm_register
(
    input                 clk,
    input                 rst,
    input      [ 31 : 0 ] d,
    output reg [ 31 : 0 ] q
);
    always @ (posedge clk or negedge rst)
        if(~rst)
            q <= 32'b0;
        else
            q <= d;
endmodule

lab_day3_02_schoolrisc/support/step1/src/schoolriscv/sr_cpu_vc.v
/*
 * schoolRISCV - small RISC-V CPU 
 *
 * originally based on Sarah L. Harris MIPS CPU 
 *                   & schoolMIPS project
 * 
 * Copyright(c) 2017-2020 Stanislav Zhelnio 
 *                        Aleksandr Romanov 
 *
 *
 *
 *          t5  vcu_data        write and read from external component
 *          t6  vcu_control     write to external, read from internal register
 *
 */ 

`include "sr_cpu.vh"



module sr_cpu_vc
(
    input           clk,        // clock
    input           rst_n,      // reset
    input   [ 4:0]  regAddr,    // debug access reg address
    output  [31:0]  regData,    // debug access reg data
    output  [31:0]  imAddr,     // instruction memory address
    input   [31:0]  imData,     // instruction memory data

    output  reg [31:0]  vcu_reg_control,    // control register for video control unit (vcu)  
    output  reg         vcu_reg_control_we, // 1 - new data in the vcu_reg_control
    output  reg [31:0]  vcu_reg_wdata,      // data register for video control unit (vcu)
    output  reg         vcu_reg_wdata_we,   // 1 - new data in the vcu_reg_wdata
    input   [31:0]      vcu_reg_rdata       // input data 
);
    //control wires
    wire        aluZero;
    wire        pcSrc;
    wire        regWrite;
    wire        aluSrc;
    wire        wdSrc;
    wire  [2:0] aluControl;

    //instruction decode wires
    wire [ 6:0] cmdOp;
    wire [ 4:0] rd;
    wire [ 2:0] cmdF3;
    wire [ 4:0] rs1;
    wire [ 4:0] rs2;
    wire [ 6:0] cmdF7;
    wire [31:0] immI;
    wire [31:0] immB;
    wire [31:0] immU;

    //program counter
    wire [31:0] pc;
    wire [31:0] pcBranch = pc + immB;
    wire [31:0] pcPlus4  = pc + 4;
    wire [31:0] pcNext   = pcSrc ? pcBranch : pcPlus4;
    sm_register r_pc(clk ,rst_n, pcNext, pc);

    //program memory access
    assign imAddr = pc >> 2;
    wire [31:0] instr = imData;

    //instruction decode
    sr_decode id (
        .instr      ( instr        ),
        .cmdOp      ( cmdOp        ),
        .rd         ( rd           ),
        .cmdF3      ( cmdF3        ),
        .rs1        ( rs1          ),
        .rs2        ( rs2          ),
        .cmdF7      ( cmdF7        ),
        .immI       ( immI         ),
        .immB       ( immB         ),
        .immU       ( immU         ) 
    );

    //register file
    wire [31:0] rd0;
    wire [31:0] rd1;
    wire [31:0] rd2;
    wire [31:0] wd3;

    sm_register_file_vc rf (
        .clk        ( clk          ),
        .a0         ( regAddr      ),
        .a1         ( rs1          ),
        .a2         ( rs2          ),
        .a3         ( rd           ),
        .rd0        ( rd0          ),
        .rd1        ( rd1          ),
        .rd2        ( rd2          ),
        .wd3        ( wd3          ),
        .we3        ( regWrite     ),
        .vcu_reg_rdata ( vcu_reg_rdata )
    );

    //debug register access
    assign regData = (regAddr != 0) ? rd0 : pc;

    // VCU register
    always @(posedge clk) begin
        if( ~rst_n )
            vcu_reg_control <= 0;
        else if( regWrite & rd==5'b11111 )
            vcu_reg_control <= wd3;
            
        if( rd==5'b11111 )
            vcu_reg_control_we <= regWrite;
        else
            vcu_reg_control_we <= 0;

        if( ~rst_n )
            vcu_reg_wdata <= 0;
        else if( regWrite & rd==5'b11110 )
            vcu_reg_wdata <= wd3;
            
        if( rd==5'b11110 )
            vcu_reg_wdata_we <= regWrite;
        else
            vcu_reg_wdata_we <= 0;

    end

    //alu
    wire [31:0] srcB = aluSrc ? immI : rd2;
    wire [31:0] aluResult;

    sr_alu alu (
        .srcA       ( rd1          ),
        .srcB       ( srcB         ),
        .oper       ( aluControl   ),
        .zero       ( aluZero      ),
        .result     ( aluResult    ) 
    );

    assign wd3 = wdSrc ? immU : aluResult;

    //control
    sr_control sm_control (
        .cmdOp      ( cmdOp        ),
        .cmdF3      ( cmdF3        ),
        .cmdF7      ( cmdF7        ),
        .aluZero    ( aluZero      ),
        .pcSrc      ( pcSrc        ),
        .regWrite   ( regWrite     ),
        .aluSrc     ( aluSrc       ),
        .wdSrc      ( wdSrc        ),
        .aluControl ( aluControl   ) 
    );

endmodule

lab_day3_02_schoolrisc/support/step3/src/schoolriscv/sm_rom.v
/*
 * schoolRISCV - small RISC-V CPU 
 *
 * originally based on Sarah L. Harris MIPS CPU 
 *                   & schoolMIPS project
 * 
 * Copyright(c) 2017-2020 Stanislav Zhelnio 
 *                        Aleksandr Romanov 
 */ 

module sm_rom
#(
    parameter PROG_NAME = "program.hex",
    parameter SIZE = 64
)
(
    input  [31:0] a,
    output [31:0] rd
);
    reg [31:0] rom [SIZE - 1:0];
    assign rd = rom [a];

    initial begin
        $readmemh (PROG_NAME, rom);
    end

endmodule

lab_day3_02_schoolrisc/support/step2/src/top.sv

`default_nettype none 

module top
#(
    parameter               is_simulation=0
)
(
  
    input   wire            clk,
    input   wire            reset_p,

    input   wire [3:0]      key_sw_p,           // key_sw_p[0]: 1 - reset cpu
                                                // key_sw_p[1]: 1 - отображение A0, 0 - отображение PC counter
                                                

    output  wire [15:0]     display_number,     // [15:12] - p0_reg_hex
                                                // [11:8]  - credit_counter
                                                // [7:4]   - p1_reg_hex
    output  wire [3:0]      led_p
    
); 

logic                           rstp;
logic   [3:0]                   key_sw_p_z1;
logic   [3:0]                   key_sw_p_z2;



logic                           p0_reset_n;
logic   [31:0]                  p0_vcu_reg_control;             //! control register for video control unit (vcu)  
logic                           p0_vcu_reg_control_we;          //! 1 - new data in the vcu_reg_control
logic   [31:0]                  p0_vcu_reg_wdata;               //! data register for video control unit (vcu)
logic                           p0_vcu_reg_wdata_we;            //! 1 - new data in the vcu_reg_wdata
logic   [31:0]                  p0_vcu_reg_rdata;               //! input data 
logic   [ 4:0]                  p0_regAddr;                     // debug access reg address
logic   [31:0]                  p0_regData;                     // debug access reg data
logic   [31:0]                  p0_imAddr;
logic   [31:0]                  p0_imData;
logic   [3:0]                   p0_reg_hex;
logic   [7:0]                   p0_reg_status;

logic   [27:0]                  tick_counter;


always @(posedge clk) begin
    rstp <= #1 reset_p | key_sw_p[0];
    p0_reset_n <= #1 ~rstp;

    key_sw_p_z1 <= #1 key_sw_p;
    key_sw_p_z2 <= #1 key_sw_p_z1;
end 

sm_rom 
#(
        .SIZE               (       128             ),
        .PROG_NAME          (   "p0_program.hex"    )
) p0_rom
(
    .a                      (       p0_imAddr       ), 
    .rd                     (       p0_imData       )
);

// sm_rom_p0
// #(
//         .SIZE               (       128             )
// ) p0_rom
// (
//     .a                      (       p0_imAddr       ), 
//     .rd                     (       p0_imData       )
// );


sr_cpu_vc  p0_sm_cpu_vc
(
    .clk                    (       clk                     ),    // clock
    .rst_n                  (       p0_reset_n              ),    // reset
    .regAddr                (       p0_regAddr              ),    // debug access reg address
    .regData                (       p0_regData              ),    // debug access reg data
    .imAddr                 (       p0_imAddr               ),
    .imData                 (       p0_imData               ),

    .vcu_reg_control        (       p0_vcu_reg_control      ),   // control register for video control unit (vcu)
    .vcu_reg_control_we     (       p0_vcu_reg_control_we   ),   // 1 - new data in the vcu_reg-control
    .vcu_reg_wdata          (       p0_vcu_reg_wdata        ),   // данные на запись
    .vcu_reg_wdata_we       (       p0_vcu_reg_wdata_we     ),   // 1 - запись данных
    .vcu_reg_rdata          (       p0_vcu_reg_rdata        )    // данные для чтения
);

assign p0_regAddr = (key_sw_p[1]) ? 5'b01010 : 5'b00000;  // кнопка 1 нажата -  p0_regData = регистр A0, не нажата - p0_regData = PC counter

assign display_number[15:8] = p0_regData[7:0];          // вывод регистра A0 или PC counter
assign display_number[7:0]  = p0_vcu_reg_wdata[7:0];    // вывод регистра T5

assign p0_vcu_reg_rdata[0] = tick_counter[27];
assign p0_vcu_reg_rdata[31:1] = '0;

always_ff @(posedge clk) begin
    if( rstp || p0_vcu_reg_wdata_we )
        tick_counter <= #1 (is_simulation) ? 28'h10 : 28'h2FAF080;
    else if( ~tick_counter[27] )
        tick_counter <= #1 tick_counter - 1;

end

assign led_p = display_number[3:0];

endmodule

`default_nettype wire

lab_day3_02_schoolrisc/support/step1/tb/tb.sv
// Code your testbench here
// or browse Examples


module tb
();
  
initial begin
  $dumpfile("dump.vcd");
  $dumpvars(5);
end
  
//   string	test_name[3:0]=
//   {
//    "test_3", 
//    "test_2", 
//    "test_1", 
//    "test_0" 
//   };
string	test_name[3:0];
int fd;
int args;

task test_finish;
  		input int 	    test_id;
  		input string	test_name;
        input int		result;
begin

    fd = $fopen( "global.txt", "a" );

    $display("");
    $display("");

    if( 1==result ) begin
        $fdisplay( fd, "test_id=%-5d test_name: %15s         TEST_PASSED", 
        test_id, test_name );
        $display(      "test_id=%-5d test_name: %15s         TEST_PASSED", 
        test_id, test_name );
    end else begin
        $fdisplay( fd, "test_id=%-5d test_name: %15s         TEST_FAILED *******", 
        test_id, test_name );
        $display(      "test_id=%-5d test_name: %15s         TEST_FAILED *******", 
        test_id, test_name );
    end

    $fclose( fd );

    $display("");
    $display("");

    $finish();
end endtask  
  
int 	        test_id=0;

logic           clk=0;
logic           reset_p;

logic [3:0]      key_sw_p;      
                                
                                

logic [15:0]     display_number;    
logic [3:0]      ar_display_number[4];
                                    
                                    
logic [3:0]      led_p;

logic            test_passed=0;
logic            test_stop=0;
logic            test_timeout=0;

always #5 clk = ~clk;

top #( .is_simulation(1) ) uut( .* );

assign ar_display_number[0] = display_number[3:0];
assign ar_display_number[1] = display_number[7:4];
assign ar_display_number[2] = display_number[11:8];
assign ar_display_number[3] = display_number[15:12];

// Main process  
initial begin  

    args=-1;

    test_name[0] = "test_0";
    test_name[1] = "test_1";
    test_name[2] = "test_2";
    test_name[3] = "test_3";

    
    if( $value$plusargs( "test_id=%0d", args )) begin
        if( args>=0 && args<2 )
        test_id = args;

        $display( "args=%d  test_id=%d", args, test_id );

    end

  $display("Hello, world! test_id=%d  name: %s  ", test_id, test_name[test_id]);

  reset_p <= #1 1;

  #200;

  @(posedge clk);
  
  reset_p <= #1 0;
  
  //@(posedge clk iff test_stop | test_timeout );
  for( int ii=0; ~(test_stop || test_timeout)  ; ii++ ) begin
    @(posedge clk);
  end


  #200;

  //test_finish( test_id, test_name[test_id], test_passed, display_number[7:4] );
  test_finish( test_id, test_name[test_id], test_passed );

end

initial begin
    #40000;
    $display();
    $display( "***************************  TIMEMOUT  ****************************"  );
    $display();
    test_timeout = 1;
end

initial begin

    test_init();

    @(negedge reset_p );

    case( test_id )
        0: begin
            // some action for test_id==0
            fork
                test_seq_p0();    
                test_seq_p1();    
                test_seq_p2();    
            join_any
           
            if( display_number[3:0]==4'b1111 )  
                test_passed = 1;
        end

        // 1: begin
        //     // some action for test_id==1
        // end

    endcase    

    test_stop = 1;
end
  
task test_init;
    key_sw_p <= '0;
endtask

// Иммитация нажатия на кнопку 1
task test_seq_p0;

    for( int loop=1;  loop<1000; loop++ ) begin

        key_sw_p[1] <= 1;    
        #500;
        key_sw_p[1] <= 0;    
        #500;

    end

endtask

// Иммитация нажатия на кнопку 2
task test_seq_p1;

    for( int loop=1;  loop<1000; loop++ ) begin        

        key_sw_p[2] <= 1;    
        #500;
        key_sw_p[2] <= 0;    
        #800;

    end


endtask


// Контроль вывода на семисегментный индикатолра
task test_seq_p2;

    for( int ii=0; ii<16; ii++ ) begin
        //@(posedge clk iff display_number[3:0]==ii ); // ожидание вывода очередной цифры на младшую цифру индикатора
        for( int kk=0; display_number[3:0]!=ii; kk++ )
            @(posedge clk);
    end

endtask


endmodule

lab_day3_02_schoolrisc/support/step2/icarus/sim_0/dump.vcd
$date
	Sat Jul  1 13:26:26 2023
$end
$version
	Icarus Verilog
$end
$timescale
	1ns
$end
$scope module tb $end
$var wire 4 ! led_p [3:0] $end
$var wire 16 " display_number [15:0] $end
$var reg 1 # clk $end
$var reg 4 $ key_sw_p [3:0] $end
$var reg 1 % reset_p $end
$var reg 1 & test_passed $end
$var reg 1 ' test_stop $end
$var reg 1 ( test_timeout $end
$var integer 32 ) args [31:0] $end
$var integer 32 * fd [31:0] $end
$var integer 32 + test_id [31:0] $end
$scope module uut $end
$var wire 1 # clk $end
$var wire 4 , key_sw_p [3:0] $end
$var wire 1 % reset_p $end
$var wire 1 - p0_vcu_reg_wdata_we $end
$var wire 32 . p0_vcu_reg_wdata [31:0] $end
$var wire 32 / p0_vcu_reg_rdata [31:0] $end
$var wire 1 0 p0_vcu_reg_control_we $end
$var wire 32 1 p0_vcu_reg_control [31:0] $end
$var wire 32 2 p0_regData [31:0] $end
$var wire 5 3 p0_regAddr [4:0] $end
$var wire 32 4 p0_imData [31:0] $end
$var wire 32 5 p0_imAddr [31:0] $end
$var wire 4 6 led_p [3:0] $end
$var wire 16 7 display_number [15:0] $end
$var parameter 32 8 is_simulation $end
$var reg 4 9 key_sw_p_z1 [3:0] $end
$var reg 4 : key_sw_p_z2 [3:0] $end
$var reg 1 ; p0_reset_n $end
$var reg 1 < rstp $end
$var reg 28 = tick_counter [27:0] $end
$scope module p0_rom $end
$var wire 32 > rd [31:0] $end
$var wire 32 ? a [31:0] $end
$var parameter 112 @ PROG_NAME $end
$var parameter 32 A SIZE $end
$upscope $end
$scope module p0_sm_cpu_vc $end
$var wire 1 # clk $end
$var wire 32 B imData [31:0] $end
$var wire 32 C instr [31:0] $end
$var wire 5 D regAddr [4:0] $end
$var wire 1 ; rst_n $end
$var wire 32 E vcu_reg_rdata [31:0] $end
$var wire 1 F wdSrc $end
$var wire 32 G wd3 [31:0] $end
$var wire 32 H srcB [31:0] $end
$var wire 5 I rs2 [4:0] $end
$var wire 5 J rs1 [4:0] $end
$var wire 1 K regWrite $end
$var wire 32 L regData [31:0] $end
$var wire 32 M rd2 [31:0] $end
$var wire 32 N rd1 [31:0] $end
$var wire 32 O rd0 [31:0] $end
$var wire 5 P rd [4:0] $end
$var wire 1 Q pcSrc $end
$var wire 32 R pcPlus4 [31:0] $end
$var wire 32 S pcNext [31:0] $end
$var wire 32 T pcBranch [31:0] $end
$var wire 32 U pc [31:0] $end
$var wire 32 V immU [31:0] $end
$var wire 32 W immI [31:0] $end
$var wire 32 X immB [31:0] $end
$var wire 32 Y imAddr [31:0] $end
$var wire 7 Z cmdOp [6:0] $end
$var wire 7 [ cmdF7 [6:0] $end
$var wire 3 \ cmdF3 [2:0] $end
$var wire 1 ] aluZero $end
$var wire 1 ^ aluSrc $end
$var wire 32 _ aluResult [31:0] $end
$var wire 3 ` aluControl [2:0] $end
$var reg 32 a vcu_reg_control [31:0] $end
$var reg 1 0 vcu_reg_control_we $end
$var reg 32 b vcu_reg_wdata [31:0] $end
$var reg 1 - vcu_reg_wdata_we $end
$scope module alu $end
$var wire 32 c srcB [31:0] $end
$var wire 1 ] zero $end
$var wire 32 d srcA [31:0] $end
$var wire 3 e oper [2:0] $end
$var reg 32 f result [31:0] $end
$upscope $end
$scope module id $end
$var wire 32 g instr [31:0] $end
$var wire 5 h rs2 [4:0] $end
$var wire 5 i rs1 [4:0] $end
$var wire 5 j rd [4:0] $end
$var wire 7 k cmdOp [6:0] $end
$var wire 7 l cmdF7 [6:0] $end
$var wire 3 m cmdF3 [2:0] $end
$var reg 32 n immB [31:0] $end
$var reg 32 o immI [31:0] $end
$var reg 32 p immU [31:0] $end
$upscope $end
$scope module r_pc $end
$var wire 1 # clk $end
$var wire 32 q d [31:0] $end
$var wire 1 ; rst $end
$var reg 32 r q [31:0] $end
$upscope $end
$scope module rf $end
$var wire 5 s a0 [4:0] $end
$var wire 5 t a1 [4:0] $end
$var wire 5 u a2 [4:0] $end
$var wire 5 v a3 [4:0] $end
$var wire 1 # clk $end
$var wire 32 w vcu_reg_rdata [31:0] $end
$var wire 32 x wd3 [31:0] $end
$var wire 1 K we3 $end
$var wire 32 y rd2 [31:0] $end
$var wire 32 z rd1 [31:0] $end
$var wire 32 { rd0 [31:0] $end
$upscope $end
$scope module sm_control $end
$var wire 1 ] aluZero $end
$var wire 3 | cmdF3 [2:0] $end
$var wire 7 } cmdF7 [6:0] $end
$var wire 7 ~ cmdOp [6:0] $end
$var wire 1 Q pcSrc $end
$var reg 3 !" aluControl [2:0] $end
$var reg 1 ^ aluSrc $end
$var reg 1 "" branch $end
$var reg 1 #" condZero $end
$var reg 1 K regWrite $end
$var reg 1 F wdSrc $end
$upscope $end
$upscope $end
$upscope $end
$scope begin $ivl_for_loop0 $end
$var integer 32 $" ii [31:0] $end
$upscope $end
$scope task test_finish $end
$var integer 32 %" result [31:0] $end
$var integer 32 &" test_id [31:0] $end
$upscope $end
$scope task test_init $end
$upscope $end
$scope task test_seq_p0 $end
$scope begin $ivl_for_loop1 $end
$var integer 32 '" loop [31:0] $end
$upscope $end
$upscope $end
$scope task test_seq_p1 $end
$scope begin $ivl_for_loop2 $end
$var integer 32 (" loop [31:0] $end
$upscope $end
$upscope $end
$scope task test_seq_p2 $end
$scope begin $ivl_for_loop3 $end
$var integer 32 )" ii [31:0] $end
$scope begin $ivl_for_loop4 $end
$var integer 32 *" kk [31:0] $end
$upscope $end
$upscope $end
$upscope $end
$upscope $end
$enddefinitions $end
$comment Show the parameter values. $end
$dumpall
b10000000 A
b111000000110000010111110111000001110010011011110110011101110010011000010110110100101110011010000110010101111000 @
b1 8
$end
#0
$dumpvars
b0 *"
b0 )"
b0 ("
b0 '"
b0 &"
b0 %"
b0 $"
x#"
x""
bx !"
bx ~
bx }
bx |
b0 {
bx z
bx y
bx x
b0x w
bx v
bx u
bx t
b0 s
bx r
bx q
bx p
bx o
bx n
bx m
bx l
bx k
bx j
bx i
bx h
bx g
bx f
bx e
bx d
bx c
bx b
bx a
bx `
bx _
x^
x]
bx \
bx [
bx Z
b0xxxxxxxxxxxxxxxxxxxxxxxxxxxxxx Y
bx X
bx W
bx V
bx U
bx T
bx S
bx R
xQ
bx P
b0 O
bx N
bx M
bx L
xK
bx J
bx I
bx H
bx G
xF
b0x E
b0 D
bx C
bx B
b0xxxxxxxxxxxxxxxxxxxxxxxxxxxxxx ?
bx >
bx =
x<
x;
bx :
bx 9
bx 7
bx 6
b0xxxxxxxxxxxxxxxxxxxxxxxxxxxxxx 5
bx 4
b0 3
bx 2
bx 1
x0
b0x /
bx .
x-
b0 ,
b0 +
b0 *
b0 )
0(
0'
0&
x%
b0 $
0#
bx "
bx !
$end
#1
1%
#5
0-
00
1#
#6
b0 9
1<
#10
0#
#15
1#
#16
b0 G
b0 x
1]
b0 _
b0 f
0Q
b100 S
b100 q
b0 H
b0 c
b0 N
b0 d
b0 z
b0 M
b0 y
b0 `
b0 e
b0 !"
0F
1^
1K
0#"
0""
b0xxxxxxxx "
b0xxxxxxxx 7
b0 V
b0 p
b1010 T
b1010 X
b1010 n
b0 W
b0 o
b10011 Z
b10011 k
b10011 ~
b1010 P
b1010 j
b1010 v
b0 \
b0 m
b0 |
b0 J
b0 i
b0 t
b0 I
b0 h
b0 u
b0 [
b0 l
b0 }
b0 2
b0 L
b10100010011 C
b10100010011 g
b10100010011 4
b10100010011 >
b10100010011 B
b0 5
b0 ?
b0 Y
b100 R
b0 U
b0 r
b0 /
b0 E
b0 w
b10000 =
b0 :
0;
#20
0#
#25
b0 !
b0 6
b0 "
b0 7
b0 .
b0 b
b0 1
b0 a
1#
#30
0#
#35
1#
#40
0#
#45
1#
#50
0#
#55
1#
#60
0#
#65
1#
#70
0#
#75
1#
#80
0#
#85
1#
#90
0#
#95
1#
#100
0#
#105
1#
#110
0#
#115
1#
#120
0#
#125
1#
#130
0#
#135
1#
#140
0#
#145
1#
#150
0#
#155
1#
#160
0#
#165
1#
#170
0#
#175
1#
#180
0#
#185
1#
#190
0#
#195
1#
#200
0#
#205
1#
#206
b1010 3
b1010 D
b1010 s
b110 $
b110 ,
b1 '"
b1 ("
b1 )"
0%
#210
0#
#215
b1 $"
b1 *"
1#
#216
b110 9
0<
#220
0#
#225
b10 *"
b10 $"
1#
#226
b110 :
1;
b1111 =
#230
0#
#235
0^
1K
b1010 W
b1010 o
b11110 X
b11110 n
b101000000000000000000000 V
b101000000000000000000000 p
b110011 Z
b110011 k
b110011 ~
b11110 P
b11110 j
b11110 v
b1010 I
b1010 h
b1010 u
b101000000000111100110011 C
b101000000000111100110011 g
b101000000000111100110011 4
b101000000000111100110011 >
b101000000000111100110011 B
b1 5
b1 ?
b1 Y
b1000 S
b1000 q
b1000 R
b100010 T
b100 U
b100 r
b11 $"
b11 *"
1#
#236
b1110 =
#240
0#
#245
b1 G
b1 x
0]
b1 _
b1 f
b1 H
b1 c
1^
1K
bx M
bx y
b101010000000000000000 V
b101010000000000000000 p
b1010 X
b1010 n
b1 W
b1 o
b10011 Z
b10011 k
b10011 ~
b1010 P
b1010 j
b1010 v
b1010 J
b1010 i
b1010 t
b1 I
b1 h
b1 u
b101010000010100010011 C
b101010000010100010011 g
b101010000010100010011 4
b101010000010100010011 >
b101010000010100010011 B
b10 5
b10 ?
b10 Y
b1100 S
b1100 q
b1100 R
b10010 T
b1000 U
b1000 r
1-
b100 *"
b100 $"
1#
#246
b1101 =
#250
0#
#255
b0 H
b0 c
b0 M
b0 y
b100000000 "
b100000000 7
b1 G
b1 x
b0 W
b0 o
b1010000000000000000 V
b1010000000000000000 p
b0 I
b0 h
b0 u
b1 2
b1 L
b1 _
b1 f
b1010000010100010011 C
b1010000010100010011 g
b1010000010100010011 4
b1010000010100010011 >
b1010000010100010011 B
b11 5
b11 ?
b11 Y
b10000 S
b10000 q
b1 O
b1 {
b1 N
b1 d
b1 z
b10000 R
b10110 T
b1100 U
b1100 r
0-
b101 $"
b101 *"
1#
#256
b10000 =
#260
0#
#265
b100 5
b100 ?
b100 Y
b10100 S
b10100 q
b10100 R
b11010 T
b10000 U
b10000 r
b110 *"
b110 $"
1#
#266
b1111 =
#270
0#
#275
b101 5
b101 ?
b101 Y
b11000 S
b11000 q
b11000 R
b11110 T
b10100 U
b10100 r
b111 $"
b111 *"
1#
#276
b1110 =
#280
0#
#285
b110 5
b110 ?
b110 Y
b11100 S
b11100 q
b11100 R
b100010 T
b11000 U
b11000 r
b1000 *"
b1000 $"
1#
#286
b1101 =
#290
0#
#295
b0 G
b0 x
1Q
1]
b0 _
b0 f
b100 `
b100 e
b100 !"
1#"
1""
0^
0K
b0 N
b0 d
b0 z
b11110000000000000000 V
b11110000000000000000 p
b0 X
b0 n
b1100011 Z
b1100011 k
b1100011 ~
b0 P
b0 j
b0 v
b11110 J
b11110 i
b11110 t
b11110000000001100011 C
b11110000000001100011 g
b11110000000001100011 4
b11110000000001100011 >
b11110000000001100011 B
b111 5
b111 ?
b111 Y
b11100 S
b11100 q
b100000 R
b11100 T
b11100 U
b11100 r
b1001 $"
b1001 *"
1#
#296
b1100 =
#300
0#
#305
b1010 *"
b1010 $"
1#
#306
b1011 =
#310
0#
